aiohttp_basicauth/__init__.py
aiohttp_basicauth-1.1.0.dist-info/LICENSE.txt
aiohttp_basicauth-1.1.0.dist-info/METADATA
aiohttp_basicauth-1.1.0.dist-info/WHEEL
aiohttp_basicauth-1.1.0.dist-info/top_level.txt
aiohttp_basicauth-1.1.0.dist-info/RECORD
