Metadata-Version: 2.1
Name: aiohttp_basicauth
Version: 1.1.0
Summary: HTTP basic authentication middleware for aiohttp 3.0+
Home-page: https://github.com/romis2012/aiohttp-basicauth
Author: Roman Snegirev
Author-email: snegiryev@gmail.com
License: Apache 2
Keywords: aiohttp http basic auth
License-File: LICENSE.txt
Requires-Dist: aiohttp>=3.0
